{
  "$schema": "https://ferrflow.com/schema/ferrflow.json",
  "workspace": {
    "remote": "origin",
    "branch": "main",
    "anonymous_telemetry": false,
    "versioning": "semver",
    "tagTemplate": "{name}/v{version}",
    "recoverMissedReleases": true,
    "releaseCommitMode": "commit",
    "releaseCommitScope": "grouped",
    "skipCi": true
  },
  "package": [
    {
      "name": "core",
      "path": "packages/core",
      "changelog": "packages/core/CHANGELOG.md",
      "versionedFiles": [
        {
          "path": "packages/core/package.json",
          "format": "json"
        }
      ],
      "hooks": {
        "postPublish": "npm run build --workspace @cdk-construct/core && npm publish --workspace @cdk-construct/core --access public"
      }
    },
    {
      "name": "aurora",
      "path": "packages/aurora",
      "changelog": "packages/aurora/CHANGELOG.md",
      "versionedFiles": [
        {
          "path": "packages/aurora/package.json",
          "format": "json"
        }
      ],
      "hooks": {
        "postPublish": "npm run build --workspace @cdk-construct/aurora && npm publish --workspace @cdk-construct/aurora --access public"
      }
    },
    {
      "name": "s3",
      "path": "packages/s3",
      "changelog": "packages/s3/CHANGELOG.md",
      "versionedFiles": [
        {
          "path": "packages/s3/package.json",
          "format": "json"
        }
      ],
      "hooks": {
        "postPublish": "npm run build --workspace @cdk-construct/s3 && npm publish --workspace @cdk-construct/s3 --access public"
      }
    },
    {
      "name": "sqs",
      "path": "packages/sqs",
      "changelog": "packages/sqs/CHANGELOG.md",
      "versionedFiles": [
        {
          "path": "packages/sqs/package.json",
          "format": "json"
        }
      ],
      "hooks": {
        "postPublish": "npm run build --workspace @cdk-construct/sqs && npm publish --workspace @cdk-construct/sqs --access public"
      }
    },
    {
      "name": "iam",
      "path": "packages/iam",
      "changelog": "packages/iam/CHANGELOG.md",
      "versionedFiles": [
        {
          "path": "packages/iam/package.json",
          "format": "json"
        }
      ],
      "hooks": {
        "postPublish": "npm run build --workspace @cdk-construct/iam && npm publish --workspace @cdk-construct/iam --access public"
      }
    },
    {
      "name": "cloudfront",
      "path": "packages/cloudfront",
      "changelog": "packages/cloudfront/CHANGELOG.md",
      "versionedFiles": [
        {
          "path": "packages/cloudfront/package.json",
          "format": "json"
        }
      ],
      "hooks": {
        "postPublish": "npm run build --workspace @cdk-construct/cloudfront && npm publish --workspace @cdk-construct/cloudfront --access public"
      }
    }
  ],
  "//": "~~ Generated by projen. To modify, edit .projenrc.ts and run \"npx projen\"."
}
